easyguix/__init__.py
easyguix/core.py
easyguix-0.1.dist-info/METADATA
easyguix-0.1.dist-info/WHEEL
easyguix-0.1.dist-info/top_level.txt
easyguix-0.1.dist-info/RECORD
