Metadata-Version: 2.4
Name: easyguix
Version: 0.1
Summary: Basit GUI oluşturmak için kolay Python arayüz kütüphanesi.
Author: Ruzgar
Keywords: gui,easy,tkinter,simple,python
Classifier: Programming Language :: Python :: 3
Classifier: Operating System :: OS Independent
Requires-Dist: pillow
Requires-Dist: plyer
Requires-Dist: tkcalendar
Requires-Dist: tkwebview2
Dynamic: author
Dynamic: classifier
Dynamic: description
Dynamic: description-content-type
Dynamic: keywords
Dynamic: requires-dist
Dynamic: summary
